strux/__init__.py
strux/batch_processing.py
strux/configs.py
strux/data_loading.py
strux/experiment.py
strux/pipeline.py
strux/results.py
strux/step.py
strux/strategies.py
strux/types.py
strux/visualization/plotting.py
strux/visualization/report_generator.py
strux/visualization/templates/annotation_report.html
strux/visualization/templates/base.html
strux/visualization/templates/comparison_report.html
strux/visualization/templates/experiment_report.html
strux/visualization/templates/report.html
strux/py.typed
strux-0.1.2.dist-info/METADATA
strux-0.1.2.dist-info/WHEEL
strux-0.1.2.dist-info/RECORD
