Metadata-Version: 2.4
Name: strux
Version: 0.1.2
Summary: Strux is a Python framework for structured outputs model versioning
Author-email: Mikhail <mikkho.ocampo@gmail.com>
Requires-Python: >=3.10
Requires-Dist: jinja2>=3.1.5
Requires-Dist: pandas>=2.2.3
Requires-Dist: plotly>=5.24.1
Requires-Dist: psycopg2-binary>=2.9.10
Requires-Dist: pydantic>=2.10.4
Requires-Dist: sqlalchemy>=2.0.36
Requires-Dist: tqdm>=4.67.1
